custom_development_standardisation/__init__.py
custom_development_standardisation/function_output.py
custom_development_standardisation-1.1.2.dist-info/METADATA
custom_development_standardisation-1.1.2.dist-info/WHEEL
custom_development_standardisation-1.1.2.dist-info/entry_points.txt
custom_development_standardisation-1.1.2.dist-info/top_level.txt
custom_development_standardisation-1.1.2.dist-info/RECORD
