Metadata-Version: 2.1
Name: custom_development_standardisation
Version: 1.1.2
Summary: All functions that assist in standardising development approaches.
Home-page: https://github.com/yourusername/your-repo
Author: Marcus
Author-email: marcusongkiansiong@gmail.com
Classifier: Programming Language :: Python :: 3
Classifier: License :: OSI Approved :: MIT License
Classifier: Operating System :: OS Independent
Requires-Python: >=3.6
